hetu/__init__.py
hetu/async_hetutensor.py
hetu/axon.py
hetu/chain_api/__init__.py
hetu/chain_api/chain.py
hetu/chain_api/commitments.py
hetu/chain_api/delegates.py
hetu/chain_api/extrinsics.py
hetu/chain_api/metagraphs.py
hetu/chain_api/neurons.py
hetu/chain_api/queries.py
hetu/chain_api/staking.py
hetu/chain_api/subnets.py
hetu/chain_api/utils.py
hetu/chain_api/wallets.py
hetu/chain_data/__init__.py
hetu/chain_data/axon_info.py
hetu/chain_data/chain_identity.py
hetu/chain_data/delegate_info.py
hetu/chain_data/delegate_info_lite.py
hetu/chain_data/dynamic_info.py
hetu/chain_data/info_base.py
hetu/chain_data/ip_info.py
hetu/chain_data/metagraph_info.py
hetu/chain_data/neuron_info.py
hetu/chain_data/neuron_info_lite.py
hetu/chain_data/prometheus_info.py
hetu/chain_data/proposal_vote_data.py
hetu/chain_data/stake_info.py
hetu/chain_data/subnet_hyperparameters.py
hetu/chain_data/subnet_identity.py
hetu/chain_data/subnet_info.py
hetu/chain_data/subnet_state.py
hetu/chain_data/utils.py
hetu/chain_data/weight_commit_info.py
hetu/client.py
hetu/config.py
hetu/dendrite.py
hetu/errors.py
hetu/hetu.py
hetu/metagraph.py
hetu/settings.py
hetu/stream.py
hetu/synapse.py
hetu/tensor.py
hetu/threadpool.py
hetu/types.py
hetu/utils/__init__.py
hetu/utils/axon_utils.py
hetu/utils/balance.py
hetu/utils/btlogging/__init__.py
hetu/utils/btlogging/console.py
hetu/utils/btlogging/defines.py
hetu/utils/btlogging/format.py
hetu/utils/btlogging/helpers.py
hetu/utils/btlogging/loggingmachine.py
hetu/utils/certifi.sh
hetu/utils/easy_imports.py
hetu/utils/formatting.py
hetu/utils/mock/__init__.py
hetu/utils/mock/hetutensor_mock.py
hetu/utils/networking.py
hetu/utils/registration/__init__.py
hetu/utils/registration/async_pow.py
hetu/utils/registration/pow.py
hetu/utils/registration/register_cuda.py
hetu/utils/subnets.py
hetu/utils/substrate_utils/__init__.py
hetu/utils/substrate_utils/hasher.py
hetu/utils/substrate_utils/storage.py
hetu/utils/version.py
hetu/utils/weight_utils.py
hetu_pysdk-0.1.0.dist-info/LICENSE
hetu_pysdk-0.1.0.dist-info/METADATA
hetu_pysdk-0.1.0.dist-info/WHEEL
hetu_pysdk-0.1.0.dist-info/RECORD
