Metadata-Version: 2.1
Name: hetu-pysdk
Version: 0.1.0
Summary: A Python SDK for interacting with the hetu blockchain (cosmos-sdk + EVM), wrapping EVM contract and cosmos RPC client features.
Home-page: https://github.com/hetu-project/hetu-pysdk
Author: Hetu Protocol
Requires-Python: >=3.12,<4.0
Classifier: Programming Language :: Python :: 3
Classifier: Programming Language :: Python :: 3.12
Classifier: Programming Language :: Python :: 3.13
Requires-Dist: colorama (>=0.4.6,<0.5.0)
Requires-Dist: cosmpy (>=0.11.1,<0.12.0)
Requires-Dist: fastapi (>=0.115.14,<0.116.0)
Requires-Dist: grpcio (>=1.73.1,<2.0.0)
Requires-Dist: msgpack-numpy-opentensor (>=0.5.0,<0.6.0)
Requires-Dist: munch (>=4.0.0,<5.0.0)
Requires-Dist: nest_asyncio (>=1.6.0,<2.0.0)
Requires-Dist: netaddr (>=1.3.0,<2.0.0)
Requires-Dist: numpy (>=2.3.1,<3.0.0)
Requires-Dist: protobuf (>=5.29.5,<6.0.0)
Requires-Dist: python-statemachine (>=2.5.0,<3.0.0)
Requires-Dist: pyyaml (>=6.0.2,<7.0.0)
Requires-Dist: requests (>=2.32.4,<3.0.0)
Requires-Dist: scalecodec (>=1.2.11,<2.0.0)
Requires-Dist: torch (>=2.7.1,<3.0.0)
Requires-Dist: twine (>=6.1.0,<7.0.0)
Requires-Dist: typing-extensions (>=4.14.0,<5.0.0)
Requires-Dist: uvicorn (>=0.35.0,<0.36.0)
Requires-Dist: web3 (>=7.12.0,<8.0.0)
Requires-Dist: wheel (>=0.45.1,<0.46.0)
Requires-Dist: xxhash (>=3.5.0,<4.0.0)
